{
  "languageserver": {
    "golang": {
      "command": "gopls",
      "rootPatterns": ["go.mod", ".vim/", ".git/", ".hg/"],
      "filetypes": ["go"],
      "initializationOptions": {
        "gocodeCompletionEnabled": true,
        "diagnosticsEnabled": true,
        "usePlaceholders": true
      }
    },
    "solidity": {
      "command": "solc",
      "args": ["--lsp"],
      "trace.server": "verbose",
      "rootPatterns": [".git/"],
      "filetypes": ["solidity"]
    }
  },
  "prettier.semi": false,
  "prettier.singleQuote": true,
  "prettier.trailingComma": "es5",
  "rust-analyzer.enable": true
}
